asdf_wcs_schemas/__init__.py
asdf_wcs_schemas/_version.py
asdf_wcs_schemas/integration.py
asdf_wcs_schemas/resources/__init__.py
asdf_wcs_schemas/resources/manifests/gwcs-1.0.0.yaml
asdf_wcs_schemas/resources/manifests/gwcs-1.0.1.yaml
asdf_wcs_schemas/resources/manifests/gwcs-1.1.0.yaml
asdf_wcs_schemas/resources/manifests/gwcs-1.2.0.yaml
asdf_wcs_schemas/resources/schemas/stsci.edu/gwcs/celestial_frame-1.0.0.yaml
asdf_wcs_schemas/resources/schemas/stsci.edu/gwcs/composite_frame-1.0.0.yaml
asdf_wcs_schemas/resources/schemas/stsci.edu/gwcs/direction_cosines-1.0.0.yaml
asdf_wcs_schemas/resources/schemas/stsci.edu/gwcs/direction_cosines-1.1.0.yaml
asdf_wcs_schemas/resources/schemas/stsci.edu/gwcs/frame-1.0.0.yaml
asdf_wcs_schemas/resources/schemas/stsci.edu/gwcs/frame2d-1.0.0.yaml
asdf_wcs_schemas/resources/schemas/stsci.edu/gwcs/grating_equation-1.0.0.yaml
asdf_wcs_schemas/resources/schemas/stsci.edu/gwcs/grating_equation-1.1.0.yaml
asdf_wcs_schemas/resources/schemas/stsci.edu/gwcs/label_mapper-1.0.0.yaml
asdf_wcs_schemas/resources/schemas/stsci.edu/gwcs/label_mapper-1.1.0.yaml
asdf_wcs_schemas/resources/schemas/stsci.edu/gwcs/regions_selector-1.0.0.yaml
asdf_wcs_schemas/resources/schemas/stsci.edu/gwcs/regions_selector-1.1.0.yaml
asdf_wcs_schemas/resources/schemas/stsci.edu/gwcs/sellmeier_glass-1.0.0.yaml
asdf_wcs_schemas/resources/schemas/stsci.edu/gwcs/sellmeier_glass-1.1.0.yaml
asdf_wcs_schemas/resources/schemas/stsci.edu/gwcs/sellmeier_zemax-1.0.0.yaml
asdf_wcs_schemas/resources/schemas/stsci.edu/gwcs/sellmeier_zemax-1.1.0.yaml
asdf_wcs_schemas/resources/schemas/stsci.edu/gwcs/snell3d-1.0.0.yaml
asdf_wcs_schemas/resources/schemas/stsci.edu/gwcs/snell3d-1.1.0.yaml
asdf_wcs_schemas/resources/schemas/stsci.edu/gwcs/spectral_frame-1.0.0.yaml
asdf_wcs_schemas/resources/schemas/stsci.edu/gwcs/spherical_cartesian-1.0.0.yaml
asdf_wcs_schemas/resources/schemas/stsci.edu/gwcs/spherical_cartesian-1.1.0.yaml
asdf_wcs_schemas/resources/schemas/stsci.edu/gwcs/step-1.0.0.yaml
asdf_wcs_schemas-0.3.0.dist-info/LICENSE
asdf_wcs_schemas-0.3.0.dist-info/METADATA
asdf_wcs_schemas-0.3.0.dist-info/WHEEL
asdf_wcs_schemas-0.3.0.dist-info/entry_points.txt
asdf_wcs_schemas-0.3.0.dist-info/top_level.txt
asdf_wcs_schemas-0.3.0.dist-info/RECORD
