Metadata-Version: 2.1
Name: asdf_wcs_schemas
Version: 0.3.0
Summary: ASDF WCS schemas
Author-email: The ASDF Developers <help@stsci.edu>
License: Copyright (C) 2021 Association of Universities for Research in Astronomy (AURA)
Project-URL: tracker, https://github.com/asdf-format/asdf-wcs-schemas/issues
Project-URL: documentation, https://asdf-wcs-schemas.readthedocs.io/en/stable
Project-URL: repository, https://github.com/asdf-format/asdf-wcs-schemas
Classifier: Programming Language :: Python
Classifier: Programming Language :: Python :: 3
Classifier: Programming Language :: Python :: 3.8
Classifier: Programming Language :: Python :: 3.9
Classifier: Programming Language :: Python :: 3.10
Classifier: Development Status :: 5 - Production/Stable
Requires-Python: >=3.8
License-File: LICENSE
Requires-Dist: asdf-standard>=1.0.1
Requires-Dist: asdf-transform-schemas>=0.3.0
Requires-Dist: asdf-unit-schemas>=0.1.0
Requires-Dist: importlib_resources>=3; python_version < "3.9"
Provides-Extra: docs
Requires-Dist: tomli; extra == "docs"
Requires-Dist: sphinx; extra == "docs"
Requires-Dist: sphinx-asdf>=0.1.3; extra == "docs"
Requires-Dist: sphinx-astropy; extra == "docs"
Requires-Dist: astropy>=5.0.4; extra == "docs"
Requires-Dist: graphviz; extra == "docs"
Requires-Dist: matplotlib; extra == "docs"
Requires-Dist: docutils; extra == "docs"
Requires-Dist: sphinx-rtd-theme; extra == "docs"
Provides-Extra: test
Requires-Dist: pytest>=4.6.0; extra == "test"
Requires-Dist: pytest-openfiles>=0.5.0; extra == "test"
Requires-Dist: asdf>=2.8.0; extra == "test"
Requires-Dist: asdf-astropy; extra == "test"
